<?xml version="1.0" encoding="ISO-8859-1" standalone="yes"?>
<List xml:lang="en">
   <Entry>
      <Name>AFGHANISTAN</Name>
      <Code>AF</Code>
   </Entry>
   <Entry>
      <Name>ALBANIA</Name>
      <Code>AL</Code>
   </Entry>
   <Entry>
      <Name>ALGERIA</Name>
      <Code>DZ</Code>
   </Entry>
   <Entry>
      <Name>AMERICAN SAMOA</Name>
      <Code>AS</Code>
   </Entry>
   <Entry>
      <Name>ANDORRA</Name>
      <Code>AD</Code>
   </Entry>
   <Entry>
      <Name>ANGOLA</Name>
      <Code>AO</Code>
   </Entry>
   <Entry>
      <Name>ANGUILLA</Name>
      <Code>AI</Code>
   </Entry>
   <Entry>
      <Name>ANTARCTICA</Name>
      <Code>AQ</Code>
   </Entry>
   <Entry>
      <Name>ANTIGUA AND BARBUDA</Name>
      <Code>AG</Code>
   </Entry>
   <Entry>
      <Name>ARGENTINA</Name>
      <Code>AR</Code>
   </Entry>
   <Entry>
      <Name>ARMENIA</Name>
      <Code>AM</Code>
   </Entry>
   <Entry>
      <Name>ARUBA</Name>
      <Code>AW</Code>
   </Entry>
   <Entry>
      <Name>AUSTRALIA</Name>
      <Code>AU</Code>
   </Entry>
   <Entry>
      <Name>AUSTRIA</Name>
      <Code>AT</Code>
   </Entry>
   <Entry>
      <Name>AZERBAIJAN</Name>
      <Code>AZ</Code>
   </Entry>
   <Entry>
      <Name>BAHAMAS</Name>
      <Code>BS</Code>
   </Entry>
   <Entry>
      <Name>BAHRAIN</Name>
      <Code>BH</Code>
   </Entry>
   <Entry>
      <Name>BANGLADESH</Name>
      <Code>BD</Code>
   </Entry>
   <Entry>
      <Name>BARBADOS</Name>
      <Code>BB</Code>
   </Entry>
   <Entry>
      <Name>BELARUS</Name>
      <Code>BY</Code>
   </Entry>
   <Entry>
      <Name>BELGIUM</Name>
      <Code>BE</Code>
   </Entry>
   <Entry>
      <Name>BELIZE</Name>
      <Code>BZ</Code>
   </Entry>
   <Entry>
      <Name>BENIN</Name>
      <Code>BJ</Code>
   </Entry>
   <Entry>
      <Name>BERMUDA</Name>
      <Code>BM</Code>
   </Entry>
   <Entry>
      <Name>BHUTAN</Name>
      <Code>BT</Code>
   </Entry>
   <Entry>
      <Name>BOLIVIA</Name>
      <Code>BO</Code>
   </Entry>
   <Entry>
      <Name>BOSNIA AND HERZEGOVINA</Name>
      <Code>BA</Code>
   </Entry>
   <Entry>
      <Name>BOTSWANA</Name>
      <Code>BW</Code>
   </Entry>
   <Entry>
      <Name>BOUVET ISLAND</Name>
      <Code>BV</Code>
   </Entry>
   <Entry>
      <Name>BRAZIL</Name>
      <Code>BR</Code>
   </Entry>
   <Entry>
      <Name>BRITISH INDIAN OCEAN TERRITORY</Name>
      <Code>IO</Code>
   </Entry>
   <Entry>
      <Name>BRUNEI DARUSSALAM</Name>
      <Code>BN</Code>
   </Entry>
   <Entry>
      <Name>BULGARIA</Name>
      <Code>BG</Code>
   </Entry>
   <Entry>
      <Name>BURKINA FASO</Name>
      <Code>BF</Code>
   </Entry>
   <Entry>
      <Name>BURUNDI</Name>
      <Code>BI</Code>
   </Entry>
   <Entry>
      <Name>CAMBODIA</Name>
      <Code>KH</Code>
   </Entry>
   <Entry>
      <Name>CAMEROON</Name>
      <Code>CM</Code>
   </Entry>
   <Entry>
      <Name>CANADA</Name>
      <Code>CA</Code>
   </Entry>
   <Entry>
      <Name>CAPE VERDE</Name>
      <Code>CV</Code>
   </Entry>
   <Entry>
      <Name>CAYMAN ISLANDS</Name>
      <Code>KY</Code>
   </Entry>
   <Entry>
      <Name>CENTRAL AFRICAN REPUBLIC</Name>
      <Code>CF</Code>
   </Entry>
   <Entry>
      <Name>CHAD</Name>
      <Code>TD</Code>
   </Entry>
   <Entry>
      <Name>CHILE</Name>
      <Code>CL</Code>
   </Entry>
   <Entry>
      <Name>CHINA</Name>
      <Code>CN</Code>
   </Entry>
   <Entry>
      <Name>CHRISTMAS ISLAND</Name>
      <Code>CX</Code>
   </Entry>
   <Entry>
      <Name>COLOMBIA</Name>
      <Code>CO</Code>
   </Entry>
   <Entry>
      <Name>COMOROS</Name>
      <Code>KM</Code>
   </Entry>
   <Entry>
      <Name>CONGO Republic</Name>
      <Code>CG</Code>
   </Entry>
   <Entry>
      <Name>CONGO DEMOCRATIC REPUBLIC</Name>
      <Code>CD</Code>
   </Entry>
   <Entry>
      <Name>COOK ISLANDS</Name>
      <Code>CK</Code>
   </Entry>
   <Entry>
      <Name>COSTA RICA</Name>
      <Code>CR</Code>
   </Entry>
   <Entry>
      <Name>CROATIA</Name>
      <Code>HR</Code>
   </Entry>
   <Entry>
      <Name>CUBA</Name>
      <Code>CU</Code>
   </Entry>
   <Entry>
      <Name>CYPRUS</Name>
      <Code>CY</Code>
   </Entry>
   <Entry>
      <Name>CZECH REPUBLIC</Name>
      <Code>CZ</Code>
   </Entry>
   <Entry>
      <Name>DENMARK</Name>
      <Code>DK</Code>
   </Entry>
   <Entry>
      <Name>DJIBOUTI</Name>
      <Code>DJ</Code>
   </Entry>
   <Entry>
      <Name>DOMINICA</Name>
      <Code>DM</Code>
   </Entry>
   <Entry>
      <Name>DOMINICAN REPUBLIC</Name>
      <Code>DO</Code>
   </Entry>
   <Entry>
      <Name>ECUADOR</Name>
      <Code>EC</Code>
   </Entry>
   <Entry>
      <Name>EGYPT</Name>
      <Code>EG</Code>
   </Entry>
   <Entry>
      <Name>EL SALVADOR</Name>
      <Code>SV</Code>
   </Entry>
   <Entry>
      <Name>EQUATORIAL GUINEA</Name>
      <Code>GQ</Code>
   </Entry>
   <Entry>
      <Name>ERITREA</Name>
      <Code>ER</Code>
   </Entry>
   <Entry>
      <Name>ESTONIA</Name>
      <Code>EE</Code>
   </Entry>
   <Entry>
      <Name>ETHIOPIA</Name>
      <Code>ET</Code>
   </Entry>
   <Entry>
      <Name>FALKLAND ISLANDS</Name>
      <Code>FK</Code>
   </Entry>
   <Entry>
      <Name>FAROE ISLANDS</Name>
      <Code>FO</Code>
   </Entry>
   <Entry>
      <Name>FIJI</Name>
      <Code>FJ</Code>
   </Entry>
   <Entry>
      <Name>FINLAND</Name>
      <Code>FI</Code>
   </Entry>
   <Entry>
      <Name>FRANCE</Name>
      <Code>FR</Code>
   </Entry>
   <Entry>
      <Name>FRENCH GUIANA</Name>
      <Code>GF</Code>
   </Entry>
   <Entry>
      <Name>FRENCH POLYNESIA</Name>
      <Code>PF</Code>
   </Entry>
   <Entry>
      <Name>FRENCH SOUTHERN TERRITORIES</Name>
      <Code>TF</Code>
   </Entry>
   <Entry>
      <Name>GABON</Name>
      <Code>GA</Code>
   </Entry>
   <Entry>
      <Name>GAMBIA</Name>
      <Code>GM</Code>
   </Entry>
   <Entry>
      <Name>GEORGIA</Name>
      <Code>GE</Code>
   </Entry>
   <Entry>
      <Name>GERMANY</Name>
      <Code>DE</Code>
   </Entry>
   <Entry>
      <Name>GHANA</Name>
      <Code>GH</Code>
   </Entry>
   <Entry>
      <Name>GIBRALTAR</Name>
      <Code>GI</Code>
   </Entry>
   <Entry>
      <Name>GREECE</Name>
      <Code>GR</Code>
   </Entry>
   <Entry>
      <Name>GREENLAND</Name>
      <Code>GL</Code>
   </Entry>
   <Entry>
      <Name>GRENADA</Name>
      <Code>GD</Code>
   </Entry>
   <Entry>
      <Name>GUAM</Name>
      <Code>GU</Code>
   </Entry>
   <Entry>
      <Name>GUATEMALA</Name>
      <Code>GT</Code>
   </Entry>
   <Entry>
   <Name>GUERNSEY</Name>
      <Code>GG</Code>
   </Entry>
   <Entry>
      <Name>GUINEA</Name>
      <Code>GN</Code>
   </Entry>
   <Entry>
      <Name>GUINEA-BISSAU</Name>
      <Code>GW</Code>
   </Entry>
   <Entry>
      <Name>GUYANA</Name>
      <Code>GY</Code>
   </Entry>
   <Entry>
      <Name>HAITI</Name>
      <Code>HT</Code>
   </Entry>
   <Entry>
      <Name>HEARD ISLAND AND MCDONALD ISLANDS</Name>
      <Code>HM</Code>
   </Entry>
   <Entry>
      <Name>HOLY SEE</Name>
      <Code>VA</Code>
   </Entry>
   <Entry>
      <Name>HONDURAS</Name>
      <Code>HN</Code>
   </Entry>
   <Entry>
      <Name>HONG KONG</Name>
      <Code>HK</Code>
   </Entry>
   <Entry>
      <Name>HUNGARY</Name>
      <Code>HU</Code>
   </Entry>
   <Entry>
      <Name>ICELAND</Name>
      <Code>IS</Code>
   </Entry>
   <Entry>
      <Name>INDIA</Name>
      <Code>IN</Code>
   </Entry>
   <Entry>
      <Name>INDONESIA</Name>
      <Code>ID</Code>
   </Entry>
   <Entry>
      <Name>IRAN</Name>
      <Code>IR</Code>
   </Entry>
   <Entry>
      <Name>IRAQ</Name>
      <Code>IQ</Code>
   </Entry>
   <Entry>
      <Name>IRELAND</Name>
      <Code>IE</Code>
   </Entry>
   <Entry>
   <Name>ISLE OF MAN</Name>
      <Code>IM</Code>
   </Entry>
   <Entry>
      <Name>ISRAEL</Name>
      <Code>IL</Code>
   </Entry>
   <Entry>
      <Name>ITALY</Name>
      <Code>IT</Code>
   </Entry>
   <Entry>
      <Name>Ivory Coast</Name>
      <Code>CI</Code>
   </Entry>
   <Entry>
      <Name>JAMAICA</Name>
      <Code>JM</Code>
   </Entry>
   <Entry>
      <Name>JAPAN</Name>
      <Code>JP</Code>
   </Entry>
   <Entry>
   <Name>JERSEY</Name>
      <Code>JE</Code>
   </Entry>
   <Entry>
      <Name>JORDAN</Name>
      <Code>JO</Code>
   </Entry>
   <Entry>
      <Name>KAZAKHSTAN</Name>
      <Code>KZ</Code>
   </Entry>
   <Entry>
      <Name>KENYA</Name>
      <Code>KE</Code>
   </Entry>
   <Entry>
      <Name>KIRIBATI</Name>
      <Code>KI</Code>
   </Entry>
   <Entry>
      <Name>KOREA North</Name>
      <Code>KP</Code>
   </Entry>
   <Entry>
      <Name>KOREA South</Name>
      <Code>KR</Code>
   </Entry>
   <Entry>
      <Name>KUWAIT</Name>
      <Code>KW</Code>
   </Entry>
   <Entry>
      <Name>KYRGYZSTAN</Name>
      <Code>KG</Code>
   </Entry>
   <Entry>
      <Name>LAOS</Name>
      <Code>LA</Code>
   </Entry>
   <Entry>
      <Name>LATVIA</Name>
      <Code>LV</Code>
   </Entry>
   <Entry>
      <Name>LEBANON</Name>
      <Code>LB</Code>
   </Entry>
   <Entry>
      <Name>LESOTHO</Name>
      <Code>LS</Code>
   </Entry>
   <Entry>
      <Name>LIBERIA</Name>
      <Code>LR</Code>
   </Entry>
   <Entry>
      <Name>LIBYA</Name>
      <Code>LY</Code>
   </Entry>
   <Entry>
      <Name>LIECHTENSTEIN</Name>
      <Code>LI</Code>
   </Entry>
   <Entry>
      <Name>LITHUANIA</Name>
      <Code>LT</Code>
   </Entry>
   <Entry>
      <Name>LUXEMBOURG</Name>
      <Code>LU</Code>
   </Entry>
   <Entry>
      <Name>MACAO</Name>
      <Code>MO</Code>
   </Entry>
   <Entry>
      <Name>MACEDONIA</Name>
      <Code>MK</Code>
   </Entry>
   <Entry>
      <Name>MADAGASCAR</Name>
      <Code>MG</Code>
   </Entry>
   <Entry>
      <Name>MALAWI</Name>
      <Code>MW</Code>
   </Entry>
   <Entry>
      <Name>MALAYSIA</Name>
      <Code>MY</Code>
   </Entry>
   <Entry>
      <Name>MALDIVES</Name>
      <Code>MV</Code>
   </Entry>
   <Entry>
      <Name>MALI</Name>
      <Code>ML</Code>
   </Entry>
   <Entry>
      <Name>MALTA</Name>
      <Code>MT</Code>
   </Entry>
   <Entry>
      <Name>MARSHALL ISLANDS</Name>
      <Code>MH</Code>
   </Entry>
   <Entry>
      <Name>MARTINIQUE</Name>
      <Code>MQ</Code>
   </Entry>
   <Entry>
      <Name>MAURITANIA</Name>
      <Code>MR</Code>
   </Entry>
   <Entry>
      <Name>MAURITIUS</Name>
      <Code>MU</Code>
   </Entry>
   <Entry>
      <Name>MAYOTTE</Name>
      <Code>YT</Code>
   </Entry>
   <Entry>
      <Name>MEXICO</Name>
      <Code>MX</Code>
   </Entry>
   <Entry>
      <Name>MICRONESIA</Name>
      <Code>FM</Code>
   </Entry>
   <Entry>
      <Name>MOLDOVA</Name>
      <Code>MD</Code>
   </Entry>
   <Entry>
      <Name>MONACO</Name>
      <Code>MC</Code>
   </Entry>
   <Entry>
      <Name>MONGOLIA</Name>
      <Code>MN</Code>
   </Entry>
   <Entry>
   <Name>MONTENEGRO</Name>
      <Code>ME</Code>
   </Entry>
   <Entry>
      <Name>MONTSERRAT</Name>
      <Code>MS</Code>
   </Entry>
   <Entry>
      <Name>MOROCCO</Name>
      <Code>MA</Code>
   </Entry>
   <Entry>
      <Name>MOZAMBIQUE</Name>
      <Code>MZ</Code>
   </Entry>
   <Entry>
      <Name>MYANMAR</Name>
      <Code>MM</Code>
   </Entry>
   <Entry>
      <Name>NAMIBIA</Name>
      <Code>NA</Code>
   </Entry>
   <Entry>
      <Name>NAURU</Name>
      <Code>NR</Code>
   </Entry>
   <Entry>
      <Name>NEPAL</Name>
      <Code>NP</Code>
   </Entry>
   <Entry>
      <Name>NETHERLANDS</Name>
      <Code>NL</Code>
   </Entry>
   <Entry>
      <Name>NEW CALEDONIA</Name>
      <Code>NC</Code>
   </Entry>
   <Entry>
      <Name>NEW ZEALAND</Name>
      <Code>NZ</Code>
   </Entry>
   <Entry>
      <Name>NICARAGUA</Name>
      <Code>NI</Code>
   </Entry>
   <Entry>
      <Name>NIGER</Name>
      <Code>NE</Code>
   </Entry>
   <Entry>
      <Name>NIGERIA</Name>
      <Code>NG</Code>
   </Entry>
   <Entry>
      <Name>NIUE</Name>
      <Code>NU</Code>
   </Entry>
   <Entry>
      <Name>NORFOLK ISLAND</Name>
      <Code>NF</Code>
   </Entry>
   <Entry>
      <Name>NORTHERN MARIANA ISLANDS</Name>
      <Code>MP</Code>
   </Entry>
   <Entry>
      <Name>NORWAY</Name>
      <Code>NO</Code>
   </Entry>
   <Entry>
      <Name>OMAN</Name>
      <Code>OM</Code>
   </Entry>
   <Entry>
      <Name>PAKISTAN</Name>
      <Code>PK</Code>
   </Entry>
   <Entry>
      <Name>PALAU</Name>
      <Code>PW</Code>
   </Entry>
   <Entry>
      <Name>PALESTINIAN TERRITORY</Name>
      <Code>PS</Code>
   </Entry>
   <Entry>
      <Name>PANAMA</Name>
      <Code>PA</Code>
   </Entry>
   <Entry>
      <Name>PAPUA NEW GUINEA</Name>
      <Code>PG</Code>
   </Entry>
   <Entry>
      <Name>PARAGUAY</Name>
      <Code>PY</Code>
   </Entry>
   <Entry>
      <Name>PERU</Name>
      <Code>PE</Code>
   </Entry>
   <Entry>
      <Name>PHILIPPINES</Name>
      <Code>PH</Code>
   </Entry>
   <Entry>
      <Name>PITCAIRN</Name>
      <Code>PN</Code>
   </Entry>
   <Entry>
      <Name>POLAND</Name>
      <Code>PL</Code>
   </Entry>
   <Entry>
      <Name>PORTUGAL</Name>
      <Code>PT</Code>
   </Entry>
   <Entry>
      <Name>PUERTO RICO</Name>
      <Code>PR</Code>
   </Entry>
   <Entry>
      <Name>QATAR</Name>
      <Code>QA</Code>
   </Entry>
   <Entry>
      <Name>ROMANIA</Name>
      <Code>RO</Code>
   </Entry>
   <Entry>
      <Name>RUSSIA</Name>
      <Code>RU</Code>
   </Entry>
   <Entry>
      <Name>RWANDA</Name>
      <Code>RW</Code>
   </Entry>
   <Entry>
      <Name>SAINT BARTHELEMY</Name>
      <Code>BL</Code>
   </Entry>
   <Entry>
      <Name>SAINT HELENA ASCENSION AND TRISTAN DA CUNHA</Name>
      <Code>SH</Code>
   </Entry>
   <Entry>
      <Name>SAINT KITTS AND NEVIS</Name>
      <Code>KN</Code>
   </Entry>
   <Entry>
      <Name>SAINT LUCIA</Name>
      <Code>LC</Code>
   </Entry>
   <Entry>
      <Name>SAINT MARTIN</Name>
      <Code>MF</Code>
   </Entry>
   <Entry>
      <Name>SAINT PIERRE AND MIQUELON</Name>
      <Code>PM</Code>
   </Entry>
   <Entry>
      <Name>SAINT VINCENT AND THE GRENADINES</Name>
      <Code>VC</Code>
   </Entry>
   <Entry>
      <Name>SAMOA</Name>
      <Code>WS</Code>
   </Entry>
   <Entry>
      <Name>SAN MARINO</Name>
      <Code>SM</Code>
   </Entry>
   <Entry>
      <Name>SAO TOME AND PRINCIPE</Name>
      <Code>ST</Code>
   </Entry>
   <Entry>
      <Name>SAUDI ARABIA</Name>
      <Code>SA</Code>
   </Entry>
   <Entry>
      <Name>SENEGAL</Name>
      <Code>SN</Code>
   </Entry>
   <Entry>
      <Name>SERBIA</Name>
      <Code>RS</Code>
   </Entry>
   <Entry>
      <Name>SEYCHELLES</Name>
      <Code>SC</Code>
   </Entry>
   <Entry>
      <Name>SIERRA LEONE</Name>
      <Code>SL</Code>
   </Entry>
   <Entry>
      <Name>SINGAPORE</Name>
      <Code>SG</Code>
   </Entry>
   <Entry>
      <Name>SLOVAKIA</Name>
      <Code>SK</Code>
   </Entry>
   <Entry>
      <Name>SLOVENIA</Name>
      <Code>SI</Code>
   </Entry>
   <Entry>
      <Name>SOLOMON ISLANDS</Name>
      <Code>SB</Code>
   </Entry>
   <Entry>
      <Name>SOMALIA</Name>
      <Code>SO</Code>
   </Entry>
   <Entry>
      <Name>SOUTH AFRICA</Name>
      <Code>ZA</Code>
   </Entry>
   <Entry>
      <Name>SPAIN</Name>
      <Code>ES</Code>
   </Entry>
   <Entry>
      <Name>SRI LANKA</Name>
      <Code>LK</Code>
   </Entry>
   <Entry>
      <Name>SUDAN</Name>
      <Code>SD</Code>
   </Entry>
   <Entry>
      <Name>SURINAME</Name>
      <Code>SR</Code>
   </Entry>
   <Entry>
      <Name>SVALBARD</Name>
      <Code>SJ</Code>
   </Entry>
   <Entry>
      <Name>SWAZILAND</Name>
      <Code>SZ</Code>
   </Entry>
   <Entry>
      <Name>SWEDEN</Name>
      <Code>SE</Code>
   </Entry>
   <Entry>
      <Name>SWITZERLAND</Name>
      <Code>CH</Code>
   </Entry>
   <Entry>
      <Name>SYRIA</Name>
      <Code>SY</Code>
   </Entry>
   <Entry>
      <Name>TAIWAN</Name>
      <Code>TW</Code>
   </Entry>
   <Entry>
      <Name>TAJIKISTAN</Name>
      <Code>TJ</Code>
   </Entry>
   <Entry>
      <Name>TANZANIA</Name>
      <Code>TZ</Code>
   </Entry>
   <Entry>
      <Name>THAILAND</Name>
      <Code>TH</Code>
   </Entry>
   <Entry>
      <Name>TIMOR-LESTE</Name>
      <Code>TL</Code>
   </Entry>
   <Entry>
      <Name>TOGO</Name>
      <Code>TG</Code>
   </Entry>
   <Entry>
      <Name>TOKELAU</Name>
      <Code>TK</Code>
   </Entry>
   <Entry>
      <Name>TONGA</Name>
      <Code>TO</Code>
   </Entry>
   <Entry>
      <Name>TRINIDAD AND TOBAGO</Name>
      <Code>TT</Code>
   </Entry>
   <Entry>
      <Name>TUNISIA</Name>
      <Code>TN</Code>
   </Entry>
   <Entry>
      <Name>TURKEY</Name>
      <Code>TR</Code>
   </Entry>
   <Entry>
      <Name>TURKMENISTAN</Name>
      <Code>TM</Code>
   </Entry>
   <Entry>
      <Name>TURKS AND CAICOS ISLANDS</Name>
      <Code>TC</Code>
   </Entry>
   <Entry>
      <Name>TUVALU</Name>
      <Code>TV</Code>
   </Entry>
   <Entry>
      <Name>UGANDA</Name>
      <Code>UG</Code>
   </Entry>
   <Entry>
      <Name>UKRAINE</Name>
      <Code>UA</Code>
   </Entry>
   <Entry>
      <Name>UNITED ARAB EMIRATES</Name>
      <Code>AE</Code>
   </Entry>
   <Entry>
      <Name>UNITED KINGDOM</Name>
      <Code>GB</Code>
   </Entry>
   <Entry>
      <Name>UNITED STATES</Name>
      <Code>US</Code>
   </Entry>
   <Entry>
      <Name>URUGUAY</Name>
      <Code>UY</Code>
   </Entry>
   <Entry>
      <Name>UZBEKISTAN</Name>
      <Code>UZ</Code>
   </Entry>
   <Entry>
      <Name>VANUATU</Name>
      <Code>VU</Code>
   </Entry>
   <Entry>
      <Name>VENEZUELA</Name>
      <Code>VE</Code>
   </Entry>
   <Entry>
      <Name>VIETNAM</Name>
      <Code>VN</Code>
   </Entry>
   <Entry>
      <Name>British VIRGIN ISLANDS</Name>
      <Code>VG</Code>
   </Entry>
   <Entry>
      <Name>VIRGIN ISLANDS</Name>
      <Code>VI</Code>
   </Entry>
   <Entry>
      <Name>WALLIS AND FUTUNA</Name>
      <Code>WF</Code>
   </Entry>
   <Entry>
      <Name>WESTERN SAHARA</Name>
      <Code>EH</Code>
   </Entry>
   <Entry>
      <Name>YEMEN</Name>
      <Code>YE</Code>
   </Entry>
   <Entry>
      <Name>ZAMBIA</Name>
      <Code>ZM</Code>
   </Entry>
   <Entry>
      <Name>ZIMBABWE</Name>
      <Code>ZW</Code>
   </Entry>
</List>
